vcfpy/__init__.py
vcfpy/bgzf.py
vcfpy/exceptions.py
vcfpy/header.py
vcfpy/parser.py
vcfpy/py.typed
vcfpy/reader.py
vcfpy/record.py
vcfpy/tabix.py
vcfpy/version.py
vcfpy/writer.py
vcfpy-0.14.1.dist-info/METADATA
vcfpy-0.14.1.dist-info/WHEEL
vcfpy-0.14.1.dist-info/licenses/AUTHORS.rst
vcfpy-0.14.1.dist-info/licenses/LICENSE
vcfpy-0.14.1.dist-info/RECORD
