Metadata-Version: 2.4
Name: vcfpy
Version: 0.14.1
Summary: Python 3 VCF library with good support for both reading and writing
Project-URL: Documentation, https://github.com/bihealth/vcfpy
Project-URL: Issues, https://github.com/bihealth/vcfpy/issues
Project-URL: Source, https://github.com/bihealth/vcfpy
Author: Manuel Holtgrewe
License-File: AUTHORS.rst
License-File: LICENSE
Classifier: Development Status :: 4 - Beta
Classifier: Intended Audience :: Developers
Classifier: License :: OSI Approved :: MIT License
Classifier: Natural Language :: English
Classifier: Programming Language :: Python :: 3
Classifier: Programming Language :: Python :: 3.10
Classifier: Programming Language :: Python :: 3.11
Classifier: Programming Language :: Python :: 3.12
Classifier: Programming Language :: Python :: 3.13
Requires-Python: >=3.10
